decon/__init__.py
decon/_decon.cpython-312-x86_64-linux-gnu.so
decon/py.typed
decontaminate-0.3.0.post4.dist-info/METADATA
decontaminate-0.3.0.post4.dist-info/WHEEL
decontaminate-0.3.0.post4.dist-info/licenses/LICENSE
decontaminate-0.3.0.post4.dist-info/RECORD
