Metadata-Version: 2.4
Name: decontaminate
Version: 0.3.0.post4
Classifier: Development Status :: 4 - Beta
Classifier: Intended Audience :: Developers
Classifier: Intended Audience :: Science/Research
Classifier: Programming Language :: Python :: 3
Classifier: Programming Language :: Python :: 3.12
Classifier: Programming Language :: Python :: 3.13
Classifier: Programming Language :: Python :: 3.14
Classifier: Programming Language :: Python :: Implementation :: CPython
Classifier: Programming Language :: Rust
Classifier: License :: OSI Approved :: Apache Software License
Classifier: Operating System :: POSIX :: Linux
Classifier: Operating System :: MacOS
Classifier: Operating System :: Microsoft :: Windows
Classifier: Topic :: Scientific/Engineering :: Artificial Intelligence
Classifier: Topic :: Software Development :: Libraries :: Python Modules
Classifier: Typing :: Typed
Requires-Dist: pytest>=8.0 ; extra == 'dev'
Provides-Extra: dev
License-File: LICENSE
Summary: Fast contamination detection for ML training data - Python bindings for decon
Keywords: machine-learning,contamination,detection,llm,evaluation,decontamination,benchmark,data-quality
Author-email: Allen Institute for AI <decon@allenai.org>
Maintainer: Vincent Zed
License-Expression: Apache-2.0
Requires-Python: >=3.12
Project-URL: Changelog, https://github.com/vincentzed/decon/releases
Project-URL: Documentation, https://github.com/vincentzed/decon/blob/main/doc/python.md
Project-URL: Homepage, https://github.com/allenai/decon
Project-URL: Issues, https://github.com/vincentzed/decon/issues
Project-URL: Repository, https://github.com/vincentzed/decon
